es_interface/__init__.py
es_interface/main.py
es_interface-0.1.0.dist-info/METADATA
es_interface-0.1.0.dist-info/WHEEL
es_interface-0.1.0.dist-info/top_level.txt
es_interface-0.1.0.dist-info/RECORD
