Metadata-Version: 2.1
Name: es-interface
Version: 0.1.0
Requires-Dist: elasticsearch
